{
    "name": "Ghulam",
    "runtime": 162,
    "genre": [
        "Action",
        "Crime",
        "Drama"
    ],
    "bio": "Jai runs errands for Ronak Singh who is a gang lord and is involved in illegal activities. Jai's brother Siddharth decides to revolt against him and Ronak after some things goes lethally awry.",
    "Country": "India",
    "poster": "https://m.media-amazon.com/images/M/MV5BOWM1NWEwY2ItYTc1OC00ZmFkLThmM2UtZjc4ZWZhYjliMjBkXkEyXkFqcGdeQXVyNjc5Mjg4Nzc@._V1_UX182_CR0,0,182,268_AL__QL50.jpg",
    "director": [
        "Vikram Bhatt"
    ],
    "language": [
        "Hindi"
    ],
    "cast": [
        {
            "imdb_id": "nm0451148",
            "name": "Aamir Khan"
        },
        {
            "imdb_id": "nm0611552",
            "name": "Rani Mukerji"
        },
        {
            "imdb_id": "nm0438496",
            "name": "Rajit Kapoor"
        },
        {
            "imdb_id": "nm0890622",
            "name": "Mita Vasisht"
        },
        {
            "imdb_id": "nm0768296",
            "name": "Sharat Saxena"
        },
        {
            "imdb_id": "nm0863120",
            "name": "Deepak Tijori"
        },
        {
            "imdb_id": "nm1014371",
            "name": "Akshay Anand"
        },
        {
            "imdb_id": "nm1200011",
            "name": "Bobby Sainy"
        },
        {
            "imdb_id": "nm0846681",
            "name": "Dalip Tahil"
        },
        {
            "imdb_id": "nm1199508",
            "name": "Raju Kher"
        },
        {
            "imdb_id": "nm1065949",
            "name": "Madhu Malhotra"
        },
        {
            "imdb_id": "nm1185319",
            "name": "Ashwin Kaushal"
        },
        {
            "imdb_id": "nm0709359",
            "name": "Ashutosh Rana"
        },
        {
            "imdb_id": "nm1234008",
            "name": "Anil Rajput"
        },
        {
            "imdb_id": "nm1835719",
            "name": "Javed Rizvi Jarehavi"
        }
    ]
}